Workbook
Name Slicer_Customer_Type: #N/A
Name Slicer_Product_Category: #N/A
Name Slicer_Region: #N/A
Name Slicer_Sales_Channel: #N/A

Sheet Sales data
A1: Product_ID | B1: Sale_Date | C1: Sales_Rep | D1: Region | E1: Sales_Amount | F1: Quantity_Sold | G1: Product_Category | H1: Unit_Cost | I1: Unit_Price | J1: Customer_Type | K1: Discount | L1: Payment_Method | M1: Sales_Channel | N1: Region_and_Sales_Rep | O1: Gross_Sales | P1: Total Cost | Q1: Net_Profit | R1: Column1
A2: 1090 | B2: 45244 | C2: Bob | D2: East | E2: 6575.91 | F2: 1 | G2: Clothing | H2: 60.28 | I2: 260.73 | J2: Returning | K2: 0.17 | L2: Cash | M2: Online | N2: East-Bob | O2: =_Salesdata[[#This Row],[Unit_Price]] * _Salesdata[[#This Row],[Quantity_Sold]] -> 260.73 | P2: =_Salesdata[[#This Row],[Unit_Cost]] * _Salesdata[[#This Row],[Quantity_Sold]] -> 60.28 | Q2: =_Salesdata[[#This Row],[Gross_Sales]] - _Salesdata[[#This Row],[Total Cost]] -> 200.45
A3: 1077 | B3: 45168 | C3: Alice | D3: West | E3: 8660.12 | F3: 25 | G3: Electronics | H3: 61.5 | I3: 258.92 | J3: New | K3: 0.17 | L3: Credit Card | M3: Online | N3: West-Alice | O3: =_Salesdata[[#This Row],[Unit_Price]] * _Salesdata[[#This Row],[Quantity_Sold]] -> 6473 | P3: =_Salesdata[[#This Row],[Unit_Cost]] * _Salesdata[[#This Row],[Quantity_Sold]] -> 1537.5 | Q3: =_Salesdata[[#This Row],[Gross_Sales]] - _Salesdata[[#This Row],[Total Cost]] -> 4935.5
A4: 1078 | B4: 45292 | C4: David | D4: East | E4: 8377.57 | F4: 42 | G4: Food | H4: 63.41 | I4: 314.93 | J4: Returning | K4: 0.03 | L4: Cash | M4: Retail | N4: East-David | O4: =_Salesdata[[#This Row],[Unit_Price]] * _Salesdata[[#This Row],[Quantity_Sold]] -> 13227.06 | P4: =_Salesdata[[#This Row],[Unit_Cost]] * _Salesdata[[#This Row],[Quantity_Sold]] -> 2663.22 | Q4: =_Salesdata[[#This Row],[Gross_Sales]] - _Salesdata[[#This Row],[Total Cost]] -> 10563.84
A5: 1026 | B5: 44963 | C5: Bob | D5: West | E5: 961.47 | F5: 34 | G5: Electronics | H5: 68.33 | I5: 219.08 | J5: New | K5: 0.02 | L5: Credit Card | M5: Online | N5: West-Bob | O5: =_Salesdata[[#This Row],[Unit_Price]] * _Salesdata[[#This Row],[Quantity_Sold]] -> 7448.72 | P5: =_Salesdata[[#This Row],[Unit_Cost]] * _Salesdata[[#This Row],[Quantity_Sold]] -> 2323.22 | Q5: =_Salesdata[[#This Row],[Gross_Sales]] - _Salesdata[[#This Row],[Total Cost]] -> 5125.5
A6: 1008 | B6: 45265 | C6: Charlie | D6: East | E6: 9583.55 | F6: 27 | G6: Electronics | H6: 68.99 | I6: 429.29 | J6: Returning | K6: 0.18 | L6: Credit Card | M6: Retail | N6: East-Charlie | O6: =_Salesdata[[#This Row],[Unit_Price]] * _Salesdata[[#This Row],[Quantity_Sold]] -> 11590.83 | P6: =_Salesdata[[#This Row],[Unit_Cost]] * _Salesdata[[#This Row],[Quantity_Sold]] -> 1862.73 | Q6: =_Salesdata[[#This Row],[Gross_Sales]] - _Salesdata[[#This Row],[Total Cost]] -> 9728.1
A7: 1100 | B7: 45186 | C7: Charlie | D7: North | E7: 4795.12 | F7: 17 | G7: Electronics | H7: 83.64 | I7: 528.49 | J7: New | K7: 0.13 | L7: Credit Card | M7: Online | N7: North-Charlie | O7: =_Salesdata[[#This Row],[Unit_Price]] * _Salesdata[[#This Row],[Quantity_Sold]] -> 8984.33 | P7: =_Salesdata[[#This Row],[Unit_Cost]] * _Salesdata[[#This Row],[Quantity_Sold]] -> 1421.88 | Q7: =_Salesdata[[#This Row],[Gross_Sales]] - _Salesdata[[#This Row],[Total Cost]] -> 7562.45
A8: 1086 | B8: 45288 | C8: Bob | D8: West | E8: 1837.37 | F8: 46 | G8: Furniture | H8: 83.86 | I8: 526.14 | J8: Returning | K8: 0.11 | L8: Credit Card | M8: Online | N8: West-Bob | O8: =_Salesdata[[#This Row],[Unit_Price]] * _Salesdata[[#This Row],[Quantity_Sold]] -> 24202.44 | P8: =_Salesdata[[#This Row],[Unit_Cost]] * _Salesdata[[#This Row],[Quantity_Sold]] -> 3857.56 | Q8: =_Salesdata[[#This Row],[Gross_Sales]] - _Salesdata[[#This Row],[Total Cost]] -> 20344.88
A9: 1086 | B9: 45219 | C9: David | D9: South | E9: 3577.07 | F9: 32 | G9: Furniture | H9: 84.86 | I9: 517.18 | J9: Returning | K9: 0.2 | L9: Credit Card | M9: Retail | N9: South-David | O9: =_Salesdata[[#This Row],[Unit_Price]] * _Salesdata[[#This Row],[Quantity_Sold]] -> 16549.76 | P9: =_Salesdata[[#This Row],[Unit_Cost]] * _Salesdata[[#This Row],[Quantity_Sold]] -> 2715.52 | Q9: =_Salesdata[[#This Row],[Gross_Sales]] - _Salesdata[[#This Row],[Total Cost]] -> 13834.24
A10: 1090 | B10: 45080 | C10: David | D10: South | E10: 6106.64 | F10: 47 | G10: Furniture | H10: 85.35 | I10: 360.54 | J10: New | K10: 0.28 | L10: Cash | M10: Online | N10: South-David | O10: =_Salesdata[[#This Row],[Unit_Price]] * _Salesdata[[#This Row],[Quantity_Sold]] -> 16945.38 | P10: =_Salesdata[[#This Row],[Unit_Cost]] * _Salesdata[[#This Row],[Quantity_Sold]] -> 4011.45 | Q10: =_Salesdata[[#This Row],[Gross_Sales]] - _Salesdata[[#This Row],[Total Cost]] -> 12933.93
A11: 1093 | B11: 45086 | C11: Bob | D11: South | E11: 4391.38 | F11: 38 | G11: Food | H11: 86.59 | I11: 390.89 | J11: Returning | K11: 0.25 | L11: Credit Card | M11: Online | N11: South-Bob | O11: =_Salesdata[[#This Row],[Unit_Price]] * _Salesdata[[#This Row],[Quantity_Sold]] -> 14853.82 | P11: =_Salesdata[[#This Row],[Unit_Cost]] * _Salesdata[[#This Row],[Quantity_Sold]] -> 3290.42 | Q11: =_Salesdata[[#This Row],[Gross_Sales]] - _Salesdata[[#This Row],[Total Cost]] -> 11563.4
A12: 1016 | B12: 45239 | C12: Charlie | D12: South | E12: 3402.92 | F12: 24 | G12: Furniture | H12: 88.44 | I12: 338.94 | J12: New | K12: 0.29 | L12: Cash | M12: Online | N12: South-Charlie | O12: =_Salesdata[[#This Row],[Unit_Price]] * _Salesdata[[#This Row],[Quantity_Sold]] -> 8134.56 | P12: =_Salesdata[[#This Row],[Unit_Cost]] * _Salesdata[[#This Row],[Quantity_Sold]] -> 2122.56 | Q12: =_Salesdata[[#This Row],[Gross_Sales]] - _Salesdata[[#This Row],[Total Cost]] -> 6012
A13: 1099 | B13: 45219 | C13: David | D13: South | E13: 7859.22 | F13: 23 | G13: Clothing | H13: 93.45 | I13: 181.62 | J13: Returning | K13: 0.3 | L13: Bank Transfer | M13: Retail | N13: South-David | O13: =_Salesdata[[#This Row],[Unit_Price]] * _Salesdata[[#This Row],[Quantity_Sold]] -> 4177.26 | P13: =_Salesdata[[#This Row],[Unit_Cost]] * _Salesdata[[#This Row],[Quantity_Sold]] -> 2149.35 | Q13: =_Salesdata[[#This Row],[Gross_Sales]] - _Salesdata[[#This Row],[Total Cost]] -> 2027.91
... A1001: 1057 | B1001: 44957 | C1001: Charlie | D1001: North | E1001: 975.01 | F1001: 36 | G1001: Food | H1001: 4995.3 | I1001: 5165.09 | J1001: Returning | K1001: 0.24 | L1001: Cash | M1001: Online | N1001: North-Charlie | O1001: =_Salesdata[[#This Row],[Unit_Price]] * _Salesdata[[#This Row],[Quantity_Sold]] -> 185943.24 | P1001: =_Salesdata[[#This Row],[Unit_Cost]] * _Salesdata[[#This Row],[Quantity_Sold]] -> 179830.8 | Q1001: =_Salesdata[[#This Row],[Gross_Sales]] - _Salesdata[[#This Row],[Total Cost]] -> 6112.44

Sheet Calculations
A1: Sum of Net_Profit | F1: Row Labels | G1: Sum of Gross_Sales
A2: 6487847.1 | F2: Food | G2: 15141886
F3: Electronics | G3: 17571041
F4: Furniture | G4: 18330281
A5: Row Labels | B5: Sum of Gross_Sales | C5: Sum of Net_Profit | F5: Clothing | G5: 19286734
A6: Jan | B6: 7488100.5 | C6: 677764.6 | F6: Grand Total | G6: 70329941
A7: Feb | B7: 5627477.4 | C7: 478053.08
A8: Mar | B8: 6008259.4 | C8: 528631.81
A9: Apr | B9: 5468497.6 | C9: 496006.82 | F9: Row Labels | G9: Sum of Net_Profit
A10: May | B10: 5800626.5 | C10: 489472.15 | F10: David | G10: 1501749.8
A11: Jun | B11: 6142561.2 | C11: 605992.2 | F11: Eve | G11: 1449081.9
A12: Jul | B12: 4751432.4 | C12: 447678.76 | F12: Alice | G12: 1294822
A13: Aug | B13: 6716190.6 | C13: 558417.69 | F13: Bob | G13: 1170800.2
A14: Sep | B14: 4557015.6 | C14: 472940.52 | F14: Charlie | G14: 1071393.2
A15: Oct | B15: 6560606.4 | C15: 584679.83 | F15: Grand Total | G15: 6487847.1
A16: Nov | B16: 4958930.2 | C16: 557812.06
A17: Dec | B17: 6250242.8 | C17: 590397.55 | F17: Sum of Gross_Sales | H17: Sum of Quantity_Sold
A18: Grand Total | B18: 70329941 | C18: 6487847.1 | F18: 70329941 | H18: 25355
B20: Sum of Profit_Margin | D20: Sum of Avg_Order_Value
B21: 0.092248721 | D21: 2773.8095

Sheet Dashboard
U10: =GETPIVOTDATA("Net_Profit",Calculations!$A$1) -> 6487847.1
U12: =GETPIVOTDATA("Profit_Margin",Calculations!$B$20) -> 0.092248721
U13: =GETPIVOTDATA("Gross_Sales",Calculations!$F$17) -> 70329941
U16: =GETPIVOTDATA("Avg_Order_Value",Calculations!$D$20) -> 2773.8095
W18: =GETPIVOTDATA("Quantity_Sold",Calculations!$H$17) -> 25355
